Metadata-Version: 2.4
Name: dissect.cobaltstrike
Version: 1.2.1
Summary: a Python library for dissecting Cobalt Strike related data
Project-URL: Homepage, https://github.com/fox-it/dissect.cobaltstrike
Project-URL: Documentation, https://dissect-cobaltstrike.readthedocs.io/
Project-URL: Source, https://github.com/fox-it/dissect.cobaltstrike
Author-email: Yun Zheng Hu <hu@fox-it.com>
License: MIT License
License-File: LICENSE
Keywords: beacon,cobaltstrike,cstruct,dissect,lark,parser,parsing
Classifier: Development Status :: 5 - Production/Stable
Classifier: Environment :: Console
Classifier: Intended Audience :: Developers
Classifier: Intended Audience :: Information Technology
Classifier: Intended Audience :: Science/Research
Classifier: License :: OSI Approved :: MIT License
Classifier: Operating System :: MacOS :: MacOS X
Classifier: Operating System :: Microsoft :: Windows
Classifier: Operating System :: POSIX
Classifier: Programming Language :: Python :: 3 :: Only
Classifier: Programming Language :: Python :: 3.9
Classifier: Programming Language :: Python :: 3.10
Classifier: Programming Language :: Python :: 3.11
Classifier: Programming Language :: Python :: 3.12
Classifier: Programming Language :: Python :: 3.13
Classifier: Topic :: Scientific/Engineering :: Information Analysis
Classifier: Topic :: Security
Classifier: Topic :: Software Development :: Libraries :: Python Modules
Classifier: Topic :: Utilities
Requires-Python: >=3.9
Requires-Dist: dissect-cstruct>=4.2
Requires-Dist: lark
Provides-Extra: c2
Requires-Dist: flow-record; extra == 'c2'
Requires-Dist: httpx; extra == 'c2'
Requires-Dist: pycryptodome; extra == 'c2'
Provides-Extra: docs
Requires-Dist: flow-record; extra == 'docs'
Requires-Dist: httpx; extra == 'docs'
Requires-Dist: ipython; extra == 'docs'
Requires-Dist: pickleshare; extra == 'docs'
Requires-Dist: pycryptodome; extra == 'docs'
Requires-Dist: pyshark; extra == 'docs'
Requires-Dist: rich; extra == 'docs'
Requires-Dist: sphinx; extra == 'docs'
Requires-Dist: sphinx-argparse-cli; extra == 'docs'
Requires-Dist: sphinx-autoapi; extra == 'docs'
Requires-Dist: sphinx-copybutton; extra == 'docs'
Requires-Dist: sphinx-rtd-theme>=2.0; extra == 'docs'
Provides-Extra: full
Requires-Dist: flow-record; extra == 'full'
Requires-Dist: httpx; extra == 'full'
Requires-Dist: pycryptodome; extra == 'full'
Requires-Dist: pyshark; extra == 'full'
Requires-Dist: rich; extra == 'full'
Provides-Extra: pcap
Requires-Dist: flow-record; extra == 'pcap'
Requires-Dist: httpx; extra == 'pcap'
Requires-Dist: pycryptodome; extra == 'pcap'
Requires-Dist: pyshark; extra == 'pcap'
Provides-Extra: test
Requires-Dist: flow-record; extra == 'test'
Requires-Dist: httpx; extra == 'test'
Requires-Dist: pycryptodome; extra == 'test'
Requires-Dist: pyshark; extra == 'test'
Requires-Dist: pytest; extra == 'test'
Requires-Dist: pytest-cov; extra == 'test'
Requires-Dist: pytest-httpserver; extra == 'test'
Requires-Dist: rich; extra == 'test'
